[
    {
      "skillName": "HTML5",
      "logo": "https://i.ibb.co/BjhHDsY/pngegg.png",
      "percentage": 85
    },
    {
      "skillName": "CSS3",
      "logo": "https://i.ibb.co/sy2Pp6C/pngegg-1.png",
      "percentage": 90
    },
    {
      "skillName": "JavaScript",
      "logo": "https://i.ibb.co/h7Bn4Wc/pngegg-2.png",
      "percentage": 80
    },
    {
      "skillName": "Tailwind",
      "logo": "https://i.ibb.co/2tNvdnY/pngwing-com.png",
      "percentage": 75
    },
    {
      "skillName": "Bootstrap",
      "logo": "https://i.ibb.co/9nrmd92/pngwing-com-1.png",
      "percentage": 75
    },
    {
      "skillName": "React",
      "logo": "https://i.ibb.co/QQWDBk4/pngwing-com-2.png",
      "percentage": 88
    },
    {
      "skillName": "Node.js",
      "logo": "https://i.ibb.co/2t3hv1y/pngegg-5.png",
      "percentage": 82
    },
    {
      "skillName": "Express.js",
      "logo": "https://i.ibb.co/T1LBMGy/kisspng-mean-solution-stack-express-js-node-js-javascript-5b1647bd733da2-082026521528186813472.png",
      "percentage": 87
    },
    {
      "skillName": "MongoDB",
      "logo": "https://i.ibb.co/3MSLz8f/pngegg-4.png",
      "percentage": 78
    },
    {
      "skillName": "Firebase",
      "logo": "https://i.ibb.co/hdfF1VZ/pngegg-3.png",
      "percentage": 76
    }
  ]
  